{
  "total": 3,
  "rows": [
    {
      "countyName": "嘉義縣",
      "orgName": "<a href='https://dalin.tzuchi-healthcare.org.tw' target='_blank'>佛教慈濟醫療財團法人大林慈濟醫院</a>",
      "phone": "05-2648000",
      "address": "<a href='https://www.google.com.tw/maps/place/嘉義縣大林鎮民生號2號' target='_blank'>嘉義縣大林鎮民生號2號</a>",
      "payDetail": "掛號費100元",
      "thisWeekRange": null,
      "thisWeekCount": 3,
      "nextWeekRange": null,
      "nextWeekCount": 3,
      "next2WeekRange": null,
      "next2WeekCount": 3,
      "next3WeekRange": null,
      "next3WeekCount": 0,
      "in4WeekTotleCount": 9,
      "editDate": "2025/11/20",
      "strTeleconsultation": "否"
    },
    {
      "countyName": "嘉義縣",
      "orgName": "<a href='https://www.vhwc.gov.tw/' target='_blank'>臺中榮民總醫院灣橋分院</a>",
      "phone": "05-2791072#7378",
      "address": "<a href='https://www.google.com.tw/maps/place/嘉義縣竹崎鄉灣橋村石麻園38號' target='_blank'>嘉義縣竹崎鄉灣橋村石麻園38號</a>",
      "payDetail": "第一次至本院建立病歷以利後續繼續治療，掛號費50元",
      "thisWeekRange": null,
      "thisWeekCount": 6,
      "nextWeekRange": null,
      "nextWeekCount": 0,
      "next2WeekRange": null,
      "next2WeekCount": 0,
      "next3WeekRange": null,
      "next3WeekCount": 0,
      "in4WeekTotleCount": 6,
      "editDate": "2025/11/19",
      "strTeleconsultation": "否"
    },
    {
      "countyName": "嘉義縣",
      "orgName": "<a href='https://respectbeing2020.mystrikingly.com/' target='_blank'>敬重自我存在心理諮商中心</a>",
      "phone": "05-2264948",
      "address": "<a href='https://www.google.com.tw/maps/place/嘉義縣民雄鄉建國路一段1020之2946號' target='_blank'>嘉義縣民雄鄉建國路一段1020之2946號</a>",
      "payDetail": "行政處理及場地費200元",
      "thisWeekRange": null,
      "thisWeekCount": 12,
      "nextWeekRange": null,
      "nextWeekCount": 12,
      "next2WeekRange": null,
      "next2WeekCount": 8,
      "next3WeekRange": null,
      "next3WeekCount": 0,
      "in4WeekTotleCount": 32,
      "editDate": "2025/11/24",
      "strTeleconsultation": "否"
    }
  ],
  "totalPages": 1
}