{
  "county": "新竹縣",
  "total": 17,
  "rows": [
    {
      "county": "新竹縣",
      "org_name": "益鼎升心理諮商所",
      "org_url": "https://www.helping.org.tw",
      "phone": "0931421391;03-6220303;03-6220305",
      "address": "新竹縣寶山鄉雙豐二街75號1樓",
      "map_url": "https://www.google.com.tw/maps/place/新竹縣寶山鄉雙豐二街75號1樓",
      "pay_detail": "無",
      "this_week": 10,
      "next_week": 10,
      "next_2_week": 10,
      "next_3_week": 0,
      "in_4_weeks": 30,
      "edit_date": "2025/09/05",
      "teleconsultation": true,
      "has_quota": true
    },
    {
      "county": "新竹縣",
      "org_name": "青空心理治療所",
      "org_url": "https://www.aozorapsyclinic.com",
      "phone": "0972-512295",
      "address": "新竹縣竹北市六家五路一段335、337號",
      "map_url": "https://www.google.com.tw/maps/place/新竹縣竹北市六家五路一段335、337號",
      "pay_detail": "行政處理費400元",
      "this_week": 1,
      "next_week": 1,
      "next_2_week": 2,
      "next_3_week": 3,
      "in_4_weeks": 7,
      "edit_date": "2025/09/08",
      "teleconsultation": true,
      "has_quota": true
    },
    {
      "county": "新竹縣",
      "org_name": "臺北榮民總醫院新竹分院",
      "org_url": "https://org.vghtpe.gov.tw/vhct/",
      "phone": "03-5962134#623",
      "address": "新竹縣竹東鎮中豐路一段81號",
      "map_url": "https://www.google.com.tw/maps/place/新竹縣竹東鎮中豐路一段81號",
      "pay_detail": "掛號費180元",
      "this_week": 4,
      "next_week": 4,
      "next_2_week": 0,
      "next_3_week": 0,
      "in_4_weeks": 8,
      "edit_date": "2025/08/26",
      "teleconsultation": false,
      "has_quota": true
    },
    {
      "county": "新竹縣",
      "org_name": "安立身心診所",
      "org_url": null,
      "phone": "03-6577622",
      "address": "新竹縣竹北市莊敬北路78號1樓",
      "map_url": "https://www.google.com.tw/maps/place/新竹縣竹北市莊敬北路78號1樓",
      "pay_detail": "民眾每次需自付200元掛號費",
      "this_week": 2,
      "next_week": 2,
      "next_2_week": 2,
      "next_3_week": 0,
      "in_4_weeks": 6,
      "edit_date": "2025/09/03",
      "teleconsultation": false,
      "has_quota": true
    },
    {
      "county": "新竹縣",
      "org_name": "培靈醫療社團法人關西醫院",
      "org_url": "https://peiling.kooco.co/",
      "phone": "03-5476399",
      "address": "新竹縣關西鎮石門33之1號",
      "map_url": "https://www.google.com.tw/maps/place/新竹縣關西鎮石門33之1號",
      "pay_detail": "無",
      "this_week": 0,
      "next_week": 0,
      "next_2_week": 0,
      "next_3_week": 0,
      "in_4_weeks": 0,
      "edit_date": "尚未更新",
      "teleconsultation": false,
      "has_quota": false
    },
    {
      "county": "新竹縣",
      "org_name": "心園心理治療所",
      "org_url": "https://www.mind-garden.org/doctor_1.aspx",
      "phone": "03-5506375",
      "address": "新竹縣竹北市勝利八街二段111號",
      "map_url": "https://www.google.com.tw/maps/place/新竹縣竹北市勝利八街二段111號",
      "pay_detail": "400掛號費",
      "this_week": 0,
      "next_week": 0,
      "next_2_week": 0,
      "next_3_week": 0,
      "in_4_weeks": 0,
      "edit_date": "2025/09/02",
      "teleconsultation": false,
      "has_quota": false
    },
    {
      "county": "新竹縣",
      "org_name": "寬心自在心理諮商所(竹北所)",
      "org_url": "https://www.openmind-counseling-center.com/",
      "phone": "03-5426695",
      "address": "新竹縣竹北市中正東路213號2樓",
      "map_url": "https://www.google.com.tw/maps/place/新竹縣竹北市中正東路213號2樓",
      "pay_detail": "18歲以上成人-掛號費200元18歲以下青少年-掛號費400元",
      "this_week": 0,
      "next_week": 0,
      "next_2_week": 0,
      "next_3_week": 0,
      "in_4_weeks": 0,
      "edit_date": "尚未更新",
      "teleconsultation": false,
      "has_quota": false
    },
    {
      "county": "新竹縣",
      "org_name": "台齡身心診所",
      "org_url": "http://www.tlwu.tw",
      "phone": "35586857",
      "address": "新竹縣竹北市文信路376號",
      "map_url": "https://www.google.com.tw/maps/place/新竹縣竹北市文信路376號",
      "pay_detail": "無",
      "this_week": 0,
      "next_week": 0,
      "next_2_week": 0,
      "next_3_week": 0,
      "in_4_weeks": 0,
      "edit_date": "尚未更新",
      "teleconsultation": false,
      "has_quota": false
    },
    {
      "county": "新竹縣",
      "org_name": "心璞藝術心理諮商所",
      "org_url": "https://www.xinpu-counseling.com/",
      "phone": "03-6685726",
      "address": "新竹縣竹北市光明六路東二段48號",
      "map_url": "https://www.google.com.tw/maps/place/新竹縣竹北市光明六路東二段48號",
      "pay_detail": "無",
      "this_week": 0,
      "next_week": 0,
      "next_2_week": 0,
      "next_3_week": 0,
      "in_4_weeks": 0,
      "edit_date": "尚未更新",
      "teleconsultation": false,
      "has_quota": false
    },
    {
      "county": "新竹縣",
      "org_name": "理路嵐天心理諮商所",
      "org_url": "https://www.facebook.com/Leeloolanlan/",
      "phone": "03-5290015",
      "address": "新竹縣寶山鄉雙豐二街25巷6號2樓",
      "map_url": "https://www.google.com.tw/maps/place/新竹縣寶山鄉雙豐二街25巷6號2樓",
      "pay_detail": "無",
      "this_week": 0,
      "next_week": 0,
      "next_2_week": 0,
      "next_3_week": 0,
      "in_4_weeks": 0,
      "edit_date": "尚未更新",
      "teleconsultation": false,
      "has_quota": false
    },
    {
      "county": "新竹縣",
      "org_name": "智諭潛能發展心理治療所",
      "org_url": "www.zhiyutherapy.com",
      "phone": "03-6571550",
      "address": "新竹縣竹北市科大二街49號1樓",
      "map_url": "https://www.google.com.tw/maps/place/新竹縣竹北市科大二街49號1樓",
      "pay_detail": "無",
      "this_week": 0,
      "next_week": 0,
      "next_2_week": 0,
      "next_3_week": 0,
      "in_4_weeks": 0,
      "edit_date": "2025/08/20",
      "teleconsultation": false,
      "has_quota": false
    },
    {
      "county": "新竹縣",
      "org_name": "星晴心理治療所",
      "org_url": "https://www.xinching-psy.com",
      "phone": "03-6578690",
      "address": "新竹縣竹北市光明六路東二段268號",
      "map_url": "https://www.google.com.tw/maps/place/新竹縣竹北市光明六路東二段268號",
      "pay_detail": "掛號費 200 元",
      "this_week": 0,
      "next_week": 0,
      "next_2_week": 0,
      "next_3_week": 0,
      "in_4_weeks": 0,
      "edit_date": "2025/08/22",
      "teleconsultation": false,
      "has_quota": false
    },
    {
      "county": "新竹縣",
      "org_name": "拾光心理諮商所",
      "org_url": "https://lightsinyou.com/",
      "phone": "03-5583800",
      "address": "新竹縣竹北市文信路23號1樓",
      "map_url": "https://www.google.com.tw/maps/place/新竹縣竹北市文信路23號1樓",
      "pay_detail": "無",
      "this_week": 0,
      "next_week": 0,
      "next_2_week": 0,
      "next_3_week": 0,
      "in_4_weeks": 0,
      "edit_date": "尚未更新",
      "teleconsultation": true,
      "has_quota": false
    },
    {
      "county": "新竹縣",
      "org_name": "六竹診所",
      "org_url": "https://www.hexa-health.com.tw/",
      "phone": "03-5505550",
      "address": "新竹縣竹北市嘉豐二街一段48號1樓",
      "map_url": "https://www.google.com.tw/maps/place/新竹縣竹北市嘉豐二街一段48號1樓",
      "pay_detail": "掛號費200元自付額50元",
      "this_week": 0,
      "next_week": 0,
      "next_2_week": 0,
      "next_3_week": 0,
      "in_4_weeks": 0,
      "edit_date": "尚未更新",
      "teleconsultation": false,
      "has_quota": false
    },
    {
      "county": "新竹縣",
      "org_name": "沐光心理諮商所",
      "org_url": "https://enlightening-cc.com/",
      "phone": "03-6578521",
      "address": "新竹縣竹北市成功11街150號2樓",
      "map_url": "https://www.google.com.tw/maps/place/新竹縣竹北市成功11街150號2樓",
      "pay_detail": "行政費500保證金600(結案後退回)",
      "this_week": 0,
      "next_week": 0,
      "next_2_week": 0,
      "next_3_week": 0,
      "in_4_weeks": 0,
      "edit_date": "尚未更新",
      "teleconsultation": true,
      "has_quota": false
    },
    {
      "county": "新竹縣",
      "org_name": "中國醫藥大學新竹附設醫院",
      "org_url": "https://www.cmu-hch.cmu.edu.tw/",
      "phone": "03-5580558分機1158",
      "address": "新竹縣竹北市興隆路一段199號",
      "map_url": "https://www.google.com.tw/maps/place/新竹縣竹北市興隆路一段199號",
      "pay_detail": "掛號費260元",
      "this_week": 0,
      "next_week": 0,
      "next_2_week": 0,
      "next_3_week": 0,
      "in_4_weeks": 0,
      "edit_date": "尚未更新",
      "teleconsultation": false,
      "has_quota": false
    },
    {
      "county": "新竹縣",
      "org_name": "天主教仁慈醫療財團法人仁慈醫院",
      "org_url": "https://www.mercy.org.tw/",
      "phone": "03-5993500",
      "address": "新竹縣湖口鄉忠孝路29號",
      "map_url": "https://www.google.com.tw/maps/place/新竹縣湖口鄉忠孝路29號",
      "pay_detail": "掛號費150元",
      "this_week": 0,
      "next_week": 0,
      "next_2_week": 0,
      "next_3_week": 0,
      "in_4_weeks": 0,
      "edit_date": "尚未更新",
      "teleconsultation": false,
      "has_quota": false
    }
  ]
}